<?xml version="1.0" encoding="utf-8"?>
<PSXApplication active="no" appType="" enabled="yes" hidden="no" id="6" startPriority="8" version="2.0">
	<name>sys_psxRelationshipSupport</name>
	<description>This applications provides query and update resources          to maintain relationships in the PSX_OBJECTRELATIONSHIP /          PSX_OBJECTRELATIONSHIPPROP and RXRELATEDCONTENT tables.</description>
	<requestRoot>sys_psxRelationshipSupport</requestRoot>
	<defaultRequestPage/>
	<appExtensionContext>application/_winkelried_1030112828154/</appExtensionContext>
	<PSXRevisionHistory>
		<PSXRevisionEntry majorVersion="1" minorVersion="0">
			<agent>BackEndTable:admin1</agent>
			<description>Saved</description>
			<time>20020929T111206718</time>
		</PSXRevisionEntry>
		<PSXRevisionEntry majorVersion="1" minorVersion="127">
			<agent>admin1</agent>
			<description>Saved</description>
			<time>20051206T124228199</time>
		</PSXRevisionEntry>
	</PSXRevisionHistory>
	<PSXAcl id="0">
		<PSXAclEntry id="0" type="user">
			<name>Default</name>
			<applicationAccessLevel dataCreate="yes" dataDelete="yes" dataQuery="yes" dataUpdate="yes" designDelete="no" designRead="no" designUpdate="no" modifyAcl="no"/>
		</PSXAclEntry>
		<PSXAclEntry id="0" type="role">
			<name>Admin</name>
			<applicationAccessLevel dataCreate="yes" dataDelete="yes" dataQuery="yes" dataUpdate="yes" designDelete="yes" designRead="yes" designUpdate="yes" modifyAcl="yes"/>
		</PSXAclEntry>
		<multiMembershipBehavior>mergeMaximumAccess</multiMembershipBehavior>
	</PSXAcl>
	<maxThreads>-1</maxThreads>
	<maxRequestTime>-1</maxRequestTime>
	<maxRequestsInQueue>-1</maxRequestsInQueue>
	<userSessionEnabled>no</userSessionEnabled>
	<userSessionTimeout>1</userSessionTimeout>
	<requestTypeHtmlParamName>DBActionType</requestTypeHtmlParamName>
	<requestTypeValueQuery>QUERY</requestTypeValueQuery>
	<requestTypeValueInsert>INSERT</requestTypeValueInsert>
	<requestTypeValueUpdate>UPDATE</requestTypeValueUpdate>
	<requestTypeValueDelete>DELETE</requestTypeValueDelete>
	<PSXDataSet id="2167">
		<name>Dataset934ids</name>
		<description>Gets the current workflow status information for the supplied content ids.</description>
		<transactionType>none</transactionType>
		<PSXQueryPipe id="463">
			<name>QueryPipe</name>
			<description/>
			<PSXBackEndDataTank id="459">
				<PSXBackEndTable id="457">
					<alias>STATES</alias>
					<table>STATES</table>
					<datasource/>
				</PSXBackEndTable>
				<PSXBackEndTable id="458">
					<alias>CONTENTSTATUS</alias>
					<table>CONTENTSTATUS</table>
					<datasource/>
				</PSXBackEndTable>
				<PSXBackEndJoin id="0" joinType="inner">
					<leftColumn>
						<PSXBackEndColumn id="0">
							<tableAlias>CONTENTSTATUS</tableAlias>
							<column>CONTENTSTATEID</column>
							<columnAlias/>
						</PSXBackEndColumn>
					</leftColumn>
					<rightColumn>
						<PSXBackEndColumn id="0">
							<tableAlias>STATES</tableAlias>
							<column>STATEID</column>
							<columnAlias/>
						</PSXBackEndColumn>
					</rightColumn>
				</PSXBackEndJoin>
				<PSXBackEndJoin id="0" joinType="inner">
					<leftColumn>
						<PSXBackEndColumn id="0">
							<tableAlias>CONTENTSTATUS</tableAlias>
							<column>WORKFLOWAPPID</column>
							<columnAlias/>
						</PSXBackEndColumn>
					</leftColumn>
					<rightColumn>
						<PSXBackEndColumn id="0">
							<tableAlias>STATES</tableAlias>
							<column>WORKFLOWAPPID</column>
							<columnAlias/>
						</PSXBackEndColumn>
					</rightColumn>
				</PSXBackEndJoin>
			</PSXBackEndDataTank>
			<PSXDataMapper id="461" returnEmptyXml="yes">
				<PSXDataMapping groupId="1" id="0">
					<PSXXmlField id="0">
						<name>CurrentStates/CurrentState/@contentId</name>
					</PSXXmlField>
					<PSXBackEndColumn id="0">
						<tableAlias>CONTENTSTATUS</tableAlias>
						<column>CONTENTID</column>
						<columnAlias/>
					</PSXBackEndColumn>
					<Conditionals/>
				</PSXDataMapping>
				<PSXDataMapping groupId="2" id="0">
					<PSXXmlField id="0">
						<name>CurrentStates/CurrentState/@isPublic</name>
					</PSXXmlField>
					<PSXBackEndColumn id="0">
						<tableAlias>STATES</tableAlias>
						<column>CONTENTVALID</column>
						<columnAlias/>
					</PSXBackEndColumn>
					<Conditionals/>
				</PSXDataMapping>
			</PSXDataMapper>
			<PSXDataSelector id="460" method="whereClause" unique="no">
				<WhereClauses>
					<PSXWhereClause id="0" omitWhenNull="no">
						<PSXConditional id="0">
							<variable>
								<PSXBackEndColumn id="0">
									<tableAlias>CONTENTSTATUS</tableAlias>
									<column>CONTENTID</column>
									<columnAlias/>
								</PSXBackEndColumn>
							</variable>
							<operator>IN</operator>
							<value>
								<PSXFunctionCall id="0">
									<name>IN-NUMBER</name>
									<PSXFunctionParamValue id="0">
										<value>
											<PSXHtmlParameter id="0">
												<name>sys_contentids</name>
											</PSXHtmlParameter>
										</value>
									</PSXFunctionParamValue>
									<PSXFunctionParamValue id="0">
										<value>
											<PSXTextLiteral id="0">
												<text/>
											</PSXTextLiteral>
										</value>
									</PSXFunctionParamValue>
								</PSXFunctionCall>
							</value>
							<boolean>AND</boolean>
						</PSXConditional>
					</PSXWhereClause>
				</WhereClauses>
				<Sorting/>
				<nativeStatement/>
				<Caching enabled="no" type="interval">
					<ageInterval>15</ageInterval>
				</Caching>
			</PSXDataSelector>
			<PSXResourceCacheSettings enabled="no" id="0">
				<Keys/>
				<Dependencies/>
			</PSXResourceCacheSettings>
		</PSXQueryPipe>
		<PSXPageDataTank id="2166">
			<schemaSource>file:CurrentStates.dtd</schemaSource>
			<actionTypeXmlField/>
		</PSXPageDataTank>
		<PSXRequestor directDataStream="no" id="0">
			<requestPage>getCurrentState</requestPage>
			<SelectionParams>
				<PSXConditional id="0">
					<variable>
						<PSXHtmlParameter id="0">
							<name>sys_contentids</name>
						</PSXHtmlParameter>
					</variable>
					<operator>IS NOT NULL</operator>
					<boolean>AND</boolean>
				</PSXConditional>
			</SelectionParams>
			<ValidationRules/>
			<characterEncoding>UTF-8</characterEncoding>
			<MimeProperties>
				<html>
					<PSXTextLiteral id="0">
						<text>text/html</text>
					</PSXTextLiteral>
				</html>
				<htm>
					<PSXTextLiteral id="0">
						<text>text/html</text>
					</PSXTextLiteral>
				</htm>
			</MimeProperties>
		</PSXRequestor>
		<PSXResultPageSet id="0">
			<PSXResultPage allowNamespaceCleanup="false" id="2168">
				<extensionsSupported/>
			</PSXResultPage>
		</PSXResultPageSet>
	</PSXDataSet>
	<PSXDataSet id="2170">
		<name>Dataset159</name>
		<description>Returns the content type information for the supplied contentid. The result document will return maximal 1 row of the CONTENTTYPE table.</description>
		<transactionType>none</transactionType>
		<PSXQueryPipe id="293">
			<name>QueryPipe</name>
			<description/>
			<PSXBackEndDataTank id="289">
				<PSXBackEndTable id="287">
					<alias>CONTENTTYPES</alias>
					<table>CONTENTTYPES</table>
					<datasource/>
				</PSXBackEndTable>
				<PSXBackEndTable id="288">
					<alias>CONTENTSTATUS</alias>
					<table>CONTENTSTATUS</table>
					<datasource/>
				</PSXBackEndTable>
				<PSXBackEndJoin id="0" joinType="inner">
					<leftColumn>
						<PSXBackEndColumn id="0">
							<tableAlias>CONTENTTYPES</tableAlias>
							<column>CONTENTTYPEID</column>
							<columnAlias/>
						</PSXBackEndColumn>
					</leftColumn>
					<rightColumn>
						<PSXBackEndColumn id="0">
							<tableAlias>CONTENTSTATUS</tableAlias>
							<column>CONTENTTYPEID</column>
							<columnAlias/>
						</PSXBackEndColumn>
					</rightColumn>
				</PSXBackEndJoin>
			</PSXBackEndDataTank>
			<PSXDataMapper id="291" returnEmptyXml="yes">
				<PSXDataMapping groupId="1" id="0">
					<PSXXmlField id="0">
						<name>getContentTypes/PSXContentType/@objectType</name>
					</PSXXmlField>
					<PSXBackEndColumn id="0">
						<tableAlias>CONTENTTYPES</tableAlias>
						<column>OBJECTTYPE</column>
						<columnAlias/>
					</PSXBackEndColumn>
					<Conditionals/>
				</PSXDataMapping>
				<PSXDataMapping groupId="1" id="0">
					<PSXXmlField id="0">
						<name>getContentTypes/PSXContentType/@hideFromMenu</name>
					</PSXXmlField>
					<PSXBackEndColumn id="0">
						<tableAlias>CONTENTTYPES</tableAlias>
						<column>HIDEFROMMENU</column>
						<columnAlias/>
					</PSXBackEndColumn>
					<Conditionals/>
				</PSXDataMapping>
				<PSXDataMapping groupId="1" id="0">
					<PSXXmlField id="0">
						<name>getContentTypes/PSXContentType/id</name>
					</PSXXmlField>
					<PSXBackEndColumn id="0">
						<tableAlias>CONTENTTYPES</tableAlias>
						<column>CONTENTTYPEID</column>
						<columnAlias/>
					</PSXBackEndColumn>
					<Conditionals/>
				</PSXDataMapping>
				<PSXDataMapping groupId="1" id="0">
					<PSXXmlField id="0">
						<name>getContentTypes/PSXContentType/name</name>
					</PSXXmlField>
					<PSXBackEndColumn id="0">
						<tableAlias>CONTENTTYPES</tableAlias>
						<column>CONTENTTYPENAME</column>
						<columnAlias/>
					</PSXBackEndColumn>
					<Conditionals/>
				</PSXDataMapping>
				<PSXDataMapping groupId="1" id="0">
					<PSXXmlField id="0">
						<name>getContentTypes/PSXContentType/description</name>
					</PSXXmlField>
					<PSXBackEndColumn id="0">
						<tableAlias>CONTENTTYPES</tableAlias>
						<column>CONTENTTYPEDESC</column>
						<columnAlias/>
					</PSXBackEndColumn>
					<Conditionals/>
				</PSXDataMapping>
				<PSXDataMapping groupId="1" id="0">
					<PSXXmlField id="0">
						<name>getContentTypes/PSXContentType/newurl</name>
					</PSXXmlField>
					<PSXBackEndColumn id="0">
						<tableAlias>CONTENTTYPES</tableAlias>
						<column>CONTENTTYPENEWREQUEST</column>
						<columnAlias/>
					</PSXBackEndColumn>
					<Conditionals/>
				</PSXDataMapping>
				<PSXDataMapping groupId="1" id="0">
					<PSXXmlField id="0">
						<name>getContentTypes/PSXContentType/queryurl</name>
					</PSXXmlField>
					<PSXBackEndColumn id="0">
						<tableAlias>CONTENTTYPES</tableAlias>
						<column>CONTENTTYPEQUERYREQUEST</column>
						<columnAlias/>
					</PSXBackEndColumn>
					<Conditionals/>
				</PSXDataMapping>
			</PSXDataMapper>
			<PSXDataSelector id="290" method="whereClause" unique="no">
				<WhereClauses>
					<PSXWhereClause id="0" omitWhenNull="no">
						<PSXConditional id="0">
							<variable>
								<PSXBackEndColumn id="0">
									<tableAlias>CONTENTSTATUS</tableAlias>
									<column>CONTENTID</column>
									<columnAlias/>
								</PSXBackEndColumn>
							</variable>
							<operator>=</operator>
							<value>
								<PSXSingleHtmlParameter id="0">
									<name>sys_contentid</name>
								</PSXSingleHtmlParameter>
							</value>
							<boolean>AND</boolean>
						</PSXConditional>
					</PSXWhereClause>
				</WhereClauses>
				<Sorting/>
				<nativeStatement/>
				<Caching enabled="no" type="interval">
					<ageInterval>15</ageInterval>
				</Caching>
			</PSXDataSelector>
			<PSXResourceCacheSettings enabled="no" id="0">
				<Keys/>
				<Dependencies/>
			</PSXResourceCacheSettings>
		</PSXQueryPipe>
		<PSXPageDataTank id="2169">
			<schemaSource>file:getContentTypes.dtd</schemaSource>
			<actionTypeXmlField/>
		</PSXPageDataTank>
		<PSXRequestor directDataStream="no" id="0">
			<requestPage>getContenttypeInfo</requestPage>
			<SelectionParams/>
			<ValidationRules/>
			<characterEncoding>UTF-8</characterEncoding>
			<MimeProperties>
				<html>
					<PSXTextLiteral id="0">
						<text>text/html</text>
					</PSXTextLiteral>
				</html>
				<htm>
					<PSXTextLiteral id="0">
						<text>text/html</text>
					</PSXTextLiteral>
				</htm>
			</MimeProperties>
		</PSXRequestor>
		<PSXResultPageSet id="0">
			<PSXResultPage allowNamespaceCleanup="false" id="2171">
				<extensionsSupported/>
			</PSXResultPage>
		</PSXResultPageSet>
	</PSXDataSet>
	<PSXDataSet id="2173">
		<name>translations</name>
		<description>Get a list of all locales that have been translated already for the supplied contentid.</description>
		<transactionType>none</transactionType>
		<PSXQueryPipe id="1624">
			<name>QueryPipe</name>
			<description/>
			<PSXBackEndDataTank id="1619">
				<PSXBackEndTable id="1615">
					<alias>PSX_RELATIONSHIPCONFIGNAME</alias>
					<table>PSX_RELATIONSHIPCONFIGNAME</table>
					<datasource/>
				</PSXBackEndTable>
				<PSXBackEndTable id="1616">
					<alias>CONTENTSTATUSCHILD</alias>
					<table>CONTENTSTATUS</table>
					<datasource/>
				</PSXBackEndTable>
				<PSXBackEndTable id="1617">
					<alias>CONTENTSTATUS</alias>
					<table>CONTENTSTATUS</table>
					<datasource/>
				</PSXBackEndTable>
				<PSXBackEndTable id="1618">
					<alias>PSX_OBJECTRELATIONSHIP</alias>
					<table>PSX_OBJECTRELATIONSHIP</table>
					<datasource/>
				</PSXBackEndTable>
				<PSXBackEndJoin id="0" joinType="inner">
					<leftColumn>
						<PSXBackEndColumn id="0">
							<tableAlias>PSX_OBJECTRELATIONSHIP</tableAlias>
							<column>CONFIG_ID</column>
							<columnAlias/>
						</PSXBackEndColumn>
					</leftColumn>
					<rightColumn>
						<PSXBackEndColumn id="0">
							<tableAlias>PSX_RELATIONSHIPCONFIGNAME</tableAlias>
							<column>CONFIG_ID</column>
							<columnAlias/>
						</PSXBackEndColumn>
					</rightColumn>
				</PSXBackEndJoin>
				<PSXBackEndJoin id="0" joinType="inner">
					<leftColumn>
						<PSXBackEndColumn id="0">
							<tableAlias>CONTENTSTATUS</tableAlias>
							<column>CONTENTID</column>
							<columnAlias/>
						</PSXBackEndColumn>
					</leftColumn>
					<rightColumn>
						<PSXBackEndColumn id="0">
							<tableAlias>PSX_OBJECTRELATIONSHIP</tableAlias>
							<column>OWNER_ID</column>
							<columnAlias/>
						</PSXBackEndColumn>
					</rightColumn>
				</PSXBackEndJoin>
				<PSXBackEndJoin id="0" joinType="inner">
					<leftColumn>
						<PSXBackEndColumn id="0">
							<tableAlias>PSX_OBJECTRELATIONSHIP</tableAlias>
							<column>DEPENDENT_ID</column>
							<columnAlias/>
						</PSXBackEndColumn>
					</leftColumn>
					<rightColumn>
						<PSXBackEndColumn id="0">
							<tableAlias>CONTENTSTATUSCHILD</tableAlias>
							<column>CONTENTID</column>
							<columnAlias/>
						</PSXBackEndColumn>
					</rightColumn>
				</PSXBackEndJoin>
			</PSXBackEndDataTank>
			<PSXDataMapper id="1622" returnEmptyXml="no">
				<PSXDataMapping groupId="1" id="0">
					<PSXXmlField id="0">
						<name>relateditemlookup/item/locale/@name</name>
					</PSXXmlField>
					<PSXBackEndColumn id="0">
						<tableAlias>CONTENTSTATUSCHILD</tableAlias>
						<column>LOCALE</column>
						<columnAlias/>
					</PSXBackEndColumn>
					<Conditionals/>
				</PSXDataMapping>
				<PSXDataMapping groupId="1" id="0">
					<PSXXmlField id="0">
						<name>relateditemlookup/item/@contentid</name>
					</PSXXmlField>
					<PSXBackEndColumn id="0">
						<tableAlias>CONTENTSTATUS</tableAlias>
						<column>CONTENTID</column>
						<columnAlias/>
					</PSXBackEndColumn>
					<Conditionals/>
				</PSXDataMapping>
				<PSXDataMapping groupId="1" id="0">
					<PSXXmlField id="0">
						<name>relateditemlookup/item/@langstring</name>
					</PSXXmlField>
					<PSXBackEndColumn id="0">
						<tableAlias>CONTENTSTATUS</tableAlias>
						<column>LOCALE</column>
						<columnAlias/>
					</PSXBackEndColumn>
					<Conditionals/>
				</PSXDataMapping>
			</PSXDataMapper>
			<PSXDataSelector id="1620" method="whereClause" unique="no">
				<WhereClauses>
					<PSXWhereClause id="0" omitWhenNull="no">
						<PSXConditional id="0">
							<variable>
								<PSXBackEndColumn id="0">
									<tableAlias>CONTENTSTATUS</tableAlias>
									<column>CONTENTID</column>
									<columnAlias/>
								</PSXBackEndColumn>
							</variable>
							<operator>IN</operator>
							<value>
								<PSXFunctionCall id="0">
									<name>IN-NUMBER</name>
									<PSXFunctionParamValue id="0">
										<value>
											<PSXHtmlParameter id="0">
												<name>sys_contentid</name>
											</PSXHtmlParameter>
										</value>
									</PSXFunctionParamValue>
									<PSXFunctionParamValue id="0">
										<value>
											<PSXNumericLiteral id="0">
												<number>-1</number>
												<format>#,##0.###</format>
											</PSXNumericLiteral>
										</value>
									</PSXFunctionParamValue>
								</PSXFunctionCall>
							</value>
							<boolean>AND</boolean>
						</PSXConditional>
					</PSXWhereClause>
					<PSXWhereClause id="0" omitWhenNull="no">
						<PSXConditional id="0">
							<variable>
								<PSXBackEndColumn id="0">
									<tableAlias>PSX_RELATIONSHIPCONFIGNAME</tableAlias>
									<column>CONFIG_NAME</column>
									<columnAlias/>
								</PSXBackEndColumn>
							</variable>
							<operator>=</operator>
							<value>
								<PSXTextLiteral id="0">
									<text>Translation</text>
								</PSXTextLiteral>
							</value>
							<boolean>AND</boolean>
						</PSXConditional>
					</PSXWhereClause>
				</WhereClauses>
				<Sorting>
					<PSXSortedColumn id="0" isAscending="yes">
						<PSXBackEndColumn id="0">
							<tableAlias>CONTENTSTATUS</tableAlias>
							<column>CONTENTID</column>
							<columnAlias/>
						</PSXBackEndColumn>
					</PSXSortedColumn>
				</Sorting>
				<nativeStatement>SELECT CONTENTSTATUSCHILD.CONTENTID AS                   CHILDCONTENTID, CONTENTSTATUSCHILD.LOCALE AS                   CHILDLOCALE, CONTENTSTATUS.CONTENTID,                   CONTENTSTATUS.LOCALE FROM CONTENTSTATUS CONTENTSTATUS,                   PSX_OBJECTRELATIONSHIP PSX_OBJECTRELATIONSHIP, CONTENTSTATUS                   CONTENTSTATUSCHILD WHERE                   CONTENTSTATUS.CONTENTID=PSX_OBJECTRELATIONSHIP.OWNERID AND                   PSX_OBJECTRELATIONSHIP.DEPENDENTID =                   CONTENTSTATUSCHILD.CONTENTID AND                   CONTENTSTATUS.CONTENTID IN                   (:"PSXSingleParam/contentids") AND                   PSX_OBJECTRELATIONSHIP.CONFIG='Translation' ORDER                   BY CONTENTSTATUS.CONTENTID ASC</nativeStatement>
				<Caching enabled="no" type="interval">
					<ageInterval>15</ageInterval>
				</Caching>
			</PSXDataSelector>
			<PSXResourceCacheSettings enabled="no" id="0">
				<Keys/>
				<Dependencies/>
			</PSXResourceCacheSettings>
		</PSXQueryPipe>
		<PSXPageDataTank id="2172">
			<schemaSource>file:relateditemlookup.dtd</schemaSource>
			<actionTypeXmlField/>
		</PSXPageDataTank>
		<PSXRequestor directDataStream="no" id="0">
			<requestPage>translations</requestPage>
			<SelectionParams/>
			<ValidationRules/>
			<characterEncoding>UTF-8</characterEncoding>
			<MimeProperties>
				<html>
					<PSXTextLiteral id="0">
						<text>text/html</text>
					</PSXTextLiteral>
				</html>
				<htm>
					<PSXTextLiteral id="0">
						<text>text/html</text>
					</PSXTextLiteral>
				</htm>
			</MimeProperties>
		</PSXRequestor>
		<PSXResultPageSet id="0">
			<PSXResultPage allowNamespaceCleanup="false" id="2174">
				<extensionsSupported/>
			</PSXResultPage>
		</PSXResultPageSet>
		<PSXResultPager id="1621">
			<maxRowsPerPage>-1</maxRowsPerPage>
			<maxPages>-1</maxPages>
			<maxPageLinks>10</maxPageLinks>
		</PSXResultPager>
	</PSXDataSet>
	<PSXDataSet id="2177">
		<name>Dataset4552</name>
		<description/>
		<transactionType>none</transactionType>
		<PSXQueryPipe id="1652">
			<name>QueryPipe</name>
			<description/>
			<PSXBackEndDataTank id="1648">
				<PSXBackEndTable id="1647">
					<alias>RXDUAL</alias>
					<table>RXDUAL</table>
					<datasource/>
				</PSXBackEndTable>
			</PSXBackEndDataTank>
			<PSXDataMapper id="1650" returnEmptyXml="no">
				<PSXDataMapping groupId="0" id="0">
					<PSXXmlField id="0">
						<name>CreateTranslation/@xml:lang</name>
					</PSXXmlField>
					<PSXUserContext id="0">
						<name>User/SessionObject/sys_lang</name>
					</PSXUserContext>
					<Conditionals/>
				</PSXDataMapping>
			</PSXDataMapper>
			<PSXDataSelector id="1649" method="whereClause" unique="no">
				<WhereClauses/>
				<Sorting/>
				<nativeStatement/>
				<Caching enabled="no" type="interval">
					<ageInterval>15</ageInterval>
				</Caching>
			</PSXDataSelector>
			<ResultDataExits>
				<PSXExtensionCallSet id="2175">
					<PSXExtensionCall id="0">
						<name>Java/global/percussion/cx/sys_CreateTranslations</name>
					</PSXExtensionCall>
				</PSXExtensionCallSet>
			</ResultDataExits>
			<PSXResourceCacheSettings enabled="no" id="0">
				<Keys/>
				<Dependencies/>
			</PSXResourceCacheSettings>
		</PSXQueryPipe>
		<PSXPageDataTank id="2176">
			<schemaSource>file:rxcx0326_RXDUAL.dtd</schemaSource>
			<actionTypeXmlField/>
		</PSXPageDataTank>
		<PSXRequestor directDataStream="no" id="0">
			<requestPage>createtranslations</requestPage>
			<SelectionParams/>
			<ValidationRules/>
			<characterEncoding>UTF-8</characterEncoding>
			<MimeProperties>
				<html>
					<PSXTextLiteral id="0">
						<text>text/html</text>
					</PSXTextLiteral>
				</html>
				<htm>
					<PSXTextLiteral id="0">
						<text>text/html</text>
					</PSXTextLiteral>
				</htm>
			</MimeProperties>
		</PSXRequestor>
		<PSXResultPageSet id="0">
			<PSXResultPage allowNamespaceCleanup="false" id="2178">
				<styleSheet>file:translationresult.xsl</styleSheet>
				<extensionsSupported/>
			</PSXResultPage>
		</PSXResultPageSet>
	</PSXDataSet>
	<PSXDataSet id="2180">
		<name>Dataset67</name>
		<description>Returns all current translations for the supplied             contentid and/or language. The returned document conforms to             the PSXRelatioship.dtd.</description>
		<transactionType>none</transactionType>
		<PSXQueryPipe id="1661">
			<name>QueryPipe</name>
			<description/>
			<PSXBackEndDataTank id="1656">
				<PSXBackEndTable id="1653">
					<alias>PSX_RELATIONSHIPCONFIGNAME</alias>
					<table>PSX_RELATIONSHIPCONFIGNAME</table>
					<datasource/>
				</PSXBackEndTable>
				<PSXBackEndTable id="1654">
					<alias>PSX_OBJECTRELATIONSHIP</alias>
					<table>PSX_OBJECTRELATIONSHIP</table>
					<datasource/>
				</PSXBackEndTable>
				<PSXBackEndTable id="1655">
					<alias>CONTENTSTATUS</alias>
					<table>CONTENTSTATUS</table>
					<datasource/>
				</PSXBackEndTable>
				<PSXBackEndJoin id="0" joinType="inner">
					<leftColumn>
						<PSXBackEndColumn id="0">
							<tableAlias>CONTENTSTATUS</tableAlias>
							<column>CONTENTID</column>
							<columnAlias/>
						</PSXBackEndColumn>
					</leftColumn>
					<rightColumn>
						<PSXBackEndColumn id="0">
							<tableAlias>PSX_OBJECTRELATIONSHIP</tableAlias>
							<column>DEPENDENT_ID</column>
							<columnAlias/>
						</PSXBackEndColumn>
					</rightColumn>
				</PSXBackEndJoin>
				<PSXBackEndJoin id="0" joinType="inner">
					<leftColumn>
						<PSXBackEndColumn id="0">
							<tableAlias>PSX_RELATIONSHIPCONFIGNAME</tableAlias>
							<column>CONFIG_ID</column>
							<columnAlias/>
						</PSXBackEndColumn>
					</leftColumn>
					<rightColumn>
						<PSXBackEndColumn id="0">
							<tableAlias>PSX_OBJECTRELATIONSHIP</tableAlias>
							<column>CONFIG_ID</column>
							<columnAlias/>
						</PSXBackEndColumn>
					</rightColumn>
				</PSXBackEndJoin>
			</PSXBackEndDataTank>
			<PSXDataMapper id="1659" returnEmptyXml="yes">
				<PSXDataMapping groupId="1" id="0">
					<PSXXmlField id="0">
						<name>PSXRelationshipSet/PSXRelationship/@id</name>
					</PSXXmlField>
					<PSXBackEndColumn id="0">
						<tableAlias>PSX_OBJECTRELATIONSHIP</tableAlias>
						<column>RID</column>
						<columnAlias/>
					</PSXBackEndColumn>
					<Conditionals/>
				</PSXDataMapping>
				<PSXDataMapping groupId="2" id="0">
					<PSXXmlField id="0">
						<name>PSXRelationshipSet/PSXRelationship/@config</name>
					</PSXXmlField>
					<PSXBackEndColumn id="0">
						<tableAlias>PSX_RELATIONSHIPCONFIGNAME</tableAlias>
						<column>CONFIG_NAME</column>
						<columnAlias/>
					</PSXBackEndColumn>
					<Conditionals/>
				</PSXDataMapping>
				<PSXDataMapping groupId="3" id="0">
					<PSXXmlField id="0">
						<name>PSXRelationshipSet/PSXRelationship/Owner/PSXLocator/CONTENTID</name>
					</PSXXmlField>
					<PSXBackEndColumn id="0">
						<tableAlias>PSX_OBJECTRELATIONSHIP</tableAlias>
						<column>OWNER_ID</column>
						<columnAlias/>
					</PSXBackEndColumn>
					<Conditionals/>
				</PSXDataMapping>
				<PSXDataMapping groupId="3" id="0">
					<PSXXmlField id="0">
						<name>PSXRelationshipSet/PSXRelationship/Owner/PSXLocator/REVISIONID</name>
					</PSXXmlField>
					<PSXBackEndColumn id="0">
						<tableAlias>PSX_OBJECTRELATIONSHIP</tableAlias>
						<column>OWNER_REVISION</column>
						<columnAlias/>
					</PSXBackEndColumn>
					<Conditionals/>
				</PSXDataMapping>
				<PSXDataMapping groupId="3" id="0">
					<PSXXmlField id="0">
						<name>PSXRelationshipSet/PSXRelationship/Dependent/PSXLocator/CONTENTID</name>
					</PSXXmlField>
					<PSXBackEndColumn id="0">
						<tableAlias>PSX_OBJECTRELATIONSHIP</tableAlias>
						<column>DEPENDENT_ID</column>
						<columnAlias/>
					</PSXBackEndColumn>
					<Conditionals/>
				</PSXDataMapping>
				<PSXDataMapping groupId="3" id="0">
					<PSXXmlField id="0">
						<name>PSXRelationshipSet/PSXRelationship/Dependent/PSXLocator/REVISIONID</name>
					</PSXXmlField>
					<PSXBackEndColumn id="0">
						<tableAlias>PSX_OBJECTRELATIONSHIP</tableAlias>
						<column>DEPENDENT_REVISION</column>
						<columnAlias/>
					</PSXBackEndColumn>
					<Conditionals/>
				</PSXDataMapping>
			</PSXDataMapper>
			<PSXDataSelector id="1657" method="whereClause" unique="no">
				<WhereClauses>
					<PSXWhereClause id="0" omitWhenNull="yes">
						<PSXConditional id="0">
							<variable>
								<PSXBackEndColumn id="0">
									<tableAlias>PSX_OBJECTRELATIONSHIP</tableAlias>
									<column>OWNER_ID</column>
									<columnAlias/>
								</PSXBackEndColumn>
							</variable>
							<operator>=</operator>
							<value>
								<PSXSingleHtmlParameter id="0">
									<name>sys_contentid</name>
								</PSXSingleHtmlParameter>
							</value>
							<boolean>AND</boolean>
						</PSXConditional>
					</PSXWhereClause>
					<PSXWhereClause id="0" omitWhenNull="no">
						<PSXConditional id="0">
							<variable>
								<PSXBackEndColumn id="0">
									<tableAlias>PSX_RELATIONSHIPCONFIGNAME</tableAlias>
									<column>CONFIG_NAME</column>
									<columnAlias/>
								</PSXBackEndColumn>
							</variable>
							<operator>=</operator>
							<value>
								<PSXTextLiteral id="0">
									<text>Translation</text>
								</PSXTextLiteral>
							</value>
							<boolean>AND</boolean>
						</PSXConditional>
					</PSXWhereClause>
					<PSXWhereClause id="0" omitWhenNull="yes">
						<PSXConditional id="0">
							<variable>
								<PSXBackEndColumn id="0">
									<tableAlias>CONTENTSTATUS</tableAlias>
									<column>LOCALE</column>
									<columnAlias/>
								</PSXBackEndColumn>
							</variable>
							<operator>=</operator>
							<value>
								<PSXSingleHtmlParameter id="0">
									<name>sys_lang</name>
								</PSXSingleHtmlParameter>
							</value>
							<boolean>AND</boolean>
						</PSXConditional>
					</PSXWhereClause>
				</WhereClauses>
				<Sorting>
					<PSXSortedColumn id="0" isAscending="yes">
						<PSXBackEndColumn id="0">
							<tableAlias>CONTENTSTATUS</tableAlias>
							<column>CONTENTID</column>
							<columnAlias/>
						</PSXBackEndColumn>
					</PSXSortedColumn>
				</Sorting>
				<nativeStatement/>
				<Caching enabled="no" type="interval">
					<ageInterval>15</ageInterval>
				</Caching>
			</PSXDataSelector>
			<PSXResourceCacheSettings enabled="no" id="0">
				<Keys/>
				<Dependencies/>
			</PSXResourceCacheSettings>
		</PSXQueryPipe>
		<PSXPageDataTank id="2179">
			<schemaSource>file:PSXRelationshipSet.dtd</schemaSource>
			<actionTypeXmlField/>
		</PSXPageDataTank>
		<PSXRequestor directDataStream="no" id="0">
			<requestPage>getTranslations</requestPage>
			<SelectionParams/>
			<ValidationRules/>
			<characterEncoding>UTF-8</characterEncoding>
			<MimeProperties>
				<html>
					<PSXTextLiteral id="0">
						<text>text/html</text>
					</PSXTextLiteral>
				</html>
				<htm>
					<PSXTextLiteral id="0">
						<text>text/html</text>
					</PSXTextLiteral>
				</htm>
			</MimeProperties>
		</PSXRequestor>
		<PSXResultPageSet id="0">
			<PSXResultPage allowNamespaceCleanup="false" id="2181">
				<extensionsSupported/>
			</PSXResultPage>
		</PSXResultPageSet>
		<PSXResultPager id="1658">
			<maxRowsPerPage>-1</maxRowsPerPage>
			<maxPages>-1</maxPages>
			<maxPageLinks>10</maxPageLinks>
		</PSXResultPager>
	</PSXDataSet>
	<PSXDataSet id="2184">
		<name>Dataset27x</name>
		<description/>
		<transactionType>none</transactionType>
		<PSXQueryPipe id="1230">
			<name>QueryPipe</name>
			<description/>
			<PSXBackEndDataTank id="1225">
				<PSXBackEndTable id="1223">
					<alias>CONTENTSTATUS</alias>
					<table>CONTENTSTATUS</table>
					<datasource/>
				</PSXBackEndTable>
				<PSXBackEndTable id="1224">
					<alias>CONTENTTYPES</alias>
					<table>CONTENTTYPES</table>
					<datasource/>
				</PSXBackEndTable>
				<PSXBackEndJoin id="0" joinType="inner">
					<leftColumn>
						<PSXBackEndColumn id="0">
							<tableAlias>CONTENTTYPES</tableAlias>
							<column>CONTENTTYPEID</column>
							<columnAlias/>
						</PSXBackEndColumn>
					</leftColumn>
					<rightColumn>
						<PSXBackEndColumn id="0">
							<tableAlias>CONTENTSTATUS</tableAlias>
							<column>CONTENTTYPEID</column>
							<columnAlias/>
						</PSXBackEndColumn>
					</rightColumn>
				</PSXBackEndJoin>
			</PSXBackEndDataTank>
			<PSXDataMapper id="1228" returnEmptyXml="no">
				<PSXDataMapping groupId="1" id="0">
					<PSXXmlField id="0">
						<name>ContentTypes/ContentType/@contenttypeid</name>
					</PSXXmlField>
					<PSXBackEndColumn id="0">
						<tableAlias>CONTENTTYPES</tableAlias>
						<column>CONTENTTYPEID</column>
						<columnAlias/>
					</PSXBackEndColumn>
					<Conditionals/>
				</PSXDataMapping>
			</PSXDataMapper>
			<PSXDataSelector id="1226" method="whereClause" unique="yes">
				<WhereClauses>
					<PSXWhereClause id="0" omitWhenNull="no">
						<PSXConditional id="0">
							<variable>
								<PSXBackEndColumn id="0">
									<tableAlias>CONTENTSTATUS</tableAlias>
									<column>CONTENTID</column>
									<columnAlias/>
								</PSXBackEndColumn>
							</variable>
							<operator>IN</operator>
							<value>
								<PSXFunctionCall id="0">
									<name>IN-NUMBER</name>
									<PSXFunctionParamValue id="0">
										<value>
											<PSXHtmlParameter id="0">
												<name>sys_contentid</name>
											</PSXHtmlParameter>
										</value>
									</PSXFunctionParamValue>
									<PSXFunctionParamValue id="0">
										<value>
											<PSXNumericLiteral id="0">
												<number>-1</number>
												<format>#,##0.###</format>
											</PSXNumericLiteral>
										</value>
									</PSXFunctionParamValue>
								</PSXFunctionCall>
							</value>
							<boolean>AND</boolean>
						</PSXConditional>
					</PSXWhereClause>
				</WhereClauses>
				<Sorting>
					<PSXSortedColumn id="0" isAscending="yes">
						<PSXBackEndColumn id="0">
							<tableAlias>CONTENTTYPES</tableAlias>
							<column>CONTENTTYPEID</column>
							<columnAlias/>
						</PSXBackEndColumn>
					</PSXSortedColumn>
				</Sorting>
				<nativeStatement>SELECT DISTINCT                   CONTENTTYPES.CONTENTTYPEID,                   CONTENTTYPES.CONTENTTYPEQUERYREQUEST FROM                   CONTENTSTATUS CONTENTSTATUS, CONTENTTYPES CONTENTTYPES                   WHERE CONTENTTYPES.CONTENTTYPEID =                   CONTENTSTATUS.CONTENTTYPEID AND                   CONTENTSTATUS.CONTENTID IN                   (:"PSXSingleParam/contentids") ORDER BY CONTENTTYPES.CONTENTTYPEID ASC</nativeStatement>
				<Caching enabled="no" type="interval">
					<ageInterval>15</ageInterval>
				</Caching>
			</PSXDataSelector>
			<ResultDataExits>
				<PSXExtensionCallSet id="2182">
					<PSXExtensionCall id="0">
						<name>Java/global/percussion/cx/sys_addAllowableWorkflowsForContentType</name>
					</PSXExtensionCall>
				</PSXExtensionCallSet>
			</ResultDataExits>
			<PSXResourceCacheSettings enabled="no" id="0">
				<Keys/>
				<Dependencies/>
			</PSXResourceCacheSettings>
		</PSXQueryPipe>
		<PSXPageDataTank id="2183">
			<schemaSource>file:commonworkflows.dtd</schemaSource>
			<actionTypeXmlField/>
		</PSXPageDataTank>
		<PSXRequestor directDataStream="no" id="0">
			<requestPage>commonworkflows</requestPage>
			<SelectionParams/>
			<ValidationRules/>
			<characterEncoding>UTF-8</characterEncoding>
			<MimeProperties>
				<html>
					<PSXTextLiteral id="0">
						<text>text/html</text>
					</PSXTextLiteral>
				</html>
				<htm>
					<PSXTextLiteral id="0">
						<text>text/html</text>
					</PSXTextLiteral>
				</htm>
			</MimeProperties>
		</PSXRequestor>
		<PSXResultPageSet id="0">
			<PSXResultPage allowNamespaceCleanup="false" id="2185">
				<extensionsSupported/>
			</PSXResultPage>
		</PSXResultPageSet>
		<PSXResultPager id="1227">
			<maxRowsPerPage>-1</maxRowsPerPage>
			<maxPages>-1</maxPages>
			<maxPageLinks>10</maxPageLinks>
		</PSXResultPager>
	</PSXDataSet>
	<PSXDataSet id="2187">
		<name>Dataset50</name>
		<description/>
		<transactionType>none</transactionType>
		<PSXQueryPipe id="54">
			<name>QueryPipe</name>
			<description/>
			<PSXBackEndDataTank id="49">
				<PSXBackEndTable id="46">
					<alias>WORKFLOWAPPS</alias>
					<table>WORKFLOWAPPS</table>
					<datasource/>
				</PSXBackEndTable>
				<PSXBackEndTable id="47">
					<alias>RXCOMMUNITY</alias>
					<table>RXCOMMUNITY</table>
					<datasource/>
				</PSXBackEndTable>
				<PSXBackEndTable id="48">
					<alias>RXWORKFLOWCOMMUNITY</alias>
					<table>RXWORKFLOWCOMMUNITY</table>
					<datasource/>
				</PSXBackEndTable>
				<PSXBackEndJoin id="0" joinType="inner">
					<leftColumn>
						<PSXBackEndColumn id="0">
							<tableAlias>WORKFLOWAPPS</tableAlias>
							<column>WORKFLOWAPPID</column>
							<columnAlias/>
						</PSXBackEndColumn>
					</leftColumn>
					<rightColumn>
						<PSXBackEndColumn id="0">
							<tableAlias>RXWORKFLOWCOMMUNITY</tableAlias>
							<column>WORKFLOWAPPID</column>
							<columnAlias/>
						</PSXBackEndColumn>
					</rightColumn>
				</PSXBackEndJoin>
				<PSXBackEndJoin id="0" joinType="inner">
					<leftColumn>
						<PSXBackEndColumn id="0">
							<tableAlias>RXCOMMUNITY</tableAlias>
							<column>COMMUNITYID</column>
							<columnAlias/>
						</PSXBackEndColumn>
					</leftColumn>
					<rightColumn>
						<PSXBackEndColumn id="0">
							<tableAlias>RXWORKFLOWCOMMUNITY</tableAlias>
							<column>COMMUNITYID</column>
							<columnAlias/>
						</PSXBackEndColumn>
					</rightColumn>
				</PSXBackEndJoin>
			</PSXBackEndDataTank>
			<PSXDataMapper id="52" returnEmptyXml="no">
				<PSXDataMapping groupId="1" id="0">
					<PSXXmlField id="0">
						<name>communityworkflowlookup/community/id</name>
					</PSXXmlField>
					<PSXBackEndColumn id="0">
						<tableAlias>RXCOMMUNITY</tableAlias>
						<column>COMMUNITYID</column>
						<columnAlias/>
					</PSXBackEndColumn>
					<Conditionals/>
				</PSXDataMapping>
				<PSXDataMapping groupId="1" id="0">
					<PSXXmlField id="0">
						<name>communityworkflowlookup/community/name</name>
					</PSXXmlField>
					<PSXExtensionCall id="0">
						<name>Java/i18n/sys_LocalizedTextLookupUser</name>
						<PSXExtensionParamValue id="0">
							<value>
								<PSXTextLiteral id="0">
									<text>psx.community</text>
								</PSXTextLiteral>
							</value>
						</PSXExtensionParamValue>
						<PSXExtensionParamValue id="0">
							<value>
								<PSXBackEndColumn id="0">
									<tableAlias>RXCOMMUNITY</tableAlias>
									<column>NAME</column>
									<columnAlias/>
								</PSXBackEndColumn>
							</value>
						</PSXExtensionParamValue>
						<PSXExtensionParamValue id="0">
							<value>
								<PSXTextLiteral id="0">
									<text/>
								</PSXTextLiteral>
							</value>
						</PSXExtensionParamValue>
						<PSXExtensionParamValue id="0">
							<value>
								<PSXTextLiteral id="0">
									<text/>
								</PSXTextLiteral>
							</value>
						</PSXExtensionParamValue>
						<PSXExtensionParamValue id="0">
							<value>
								<PSXTextLiteral id="0">
									<text/>
								</PSXTextLiteral>
							</value>
						</PSXExtensionParamValue>
						<PSXExtensionParamValue id="0">
							<value>
								<PSXTextLiteral id="0">
									<text/>
								</PSXTextLiteral>
							</value>
						</PSXExtensionParamValue>
						<PSXExtensionParamValue id="0">
							<value>
								<PSXTextLiteral id="0">
									<text/>
								</PSXTextLiteral>
							</value>
						</PSXExtensionParamValue>
					</PSXExtensionCall>
					<Conditionals/>
				</PSXDataMapping>
				<PSXDataMapping groupId="2" id="0">
					<PSXXmlField id="0">
						<name>communityworkflowlookup/community/workflow/id</name>
					</PSXXmlField>
					<PSXBackEndColumn id="0">
						<tableAlias>WORKFLOWAPPS</tableAlias>
						<column>WORKFLOWAPPID</column>
						<columnAlias/>
					</PSXBackEndColumn>
					<Conditionals/>
				</PSXDataMapping>
				<PSXDataMapping groupId="2" id="0">
					<PSXXmlField id="0">
						<name>communityworkflowlookup/community/workflow/name</name>
					</PSXXmlField>
					<PSXExtensionCall id="0">
						<name>Java/i18n/sys_LocalizedTextLookupUser</name>
						<PSXExtensionParamValue id="0">
							<value>
								<PSXTextLiteral id="0">
									<text>psx.workflow.workflow</text>
								</PSXTextLiteral>
							</value>
						</PSXExtensionParamValue>
						<PSXExtensionParamValue id="0">
							<value>
								<PSXBackEndColumn id="0">
									<tableAlias>WORKFLOWAPPS</tableAlias>
									<column>WORKFLOWAPPID</column>
									<columnAlias/>
								</PSXBackEndColumn>
							</value>
						</PSXExtensionParamValue>
						<PSXExtensionParamValue id="0">
							<value>
								<PSXBackEndColumn id="0">
									<tableAlias>WORKFLOWAPPS</tableAlias>
									<column>WORKFLOWAPPNAME</column>
									<columnAlias/>
								</PSXBackEndColumn>
							</value>
						</PSXExtensionParamValue>
						<PSXExtensionParamValue id="0">
							<value>
								<PSXTextLiteral id="0">
									<text/>
								</PSXTextLiteral>
							</value>
						</PSXExtensionParamValue>
						<PSXExtensionParamValue id="0">
							<value>
								<PSXTextLiteral id="0">
									<text/>
								</PSXTextLiteral>
							</value>
						</PSXExtensionParamValue>
						<PSXExtensionParamValue id="0">
							<value>
								<PSXTextLiteral id="0">
									<text/>
								</PSXTextLiteral>
							</value>
						</PSXExtensionParamValue>
						<PSXExtensionParamValue id="0">
							<value>
								<PSXTextLiteral id="0">
									<text/>
								</PSXTextLiteral>
							</value>
						</PSXExtensionParamValue>
						<PSXExtensionParamValue id="0">
							<value>
								<PSXTextLiteral id="0">
									<text/>
								</PSXTextLiteral>
							</value>
						</PSXExtensionParamValue>
					</PSXExtensionCall>
					<Conditionals/>
				</PSXDataMapping>
			</PSXDataMapper>
			<PSXDataSelector id="50" method="whereClause" unique="no">
				<WhereClauses/>
				<Sorting>
					<PSXSortedColumn id="0" isAscending="yes">
						<PSXBackEndColumn id="0">
							<tableAlias>RXCOMMUNITY</tableAlias>
							<column>NAME</column>
							<columnAlias/>
						</PSXBackEndColumn>
					</PSXSortedColumn>
					<PSXSortedColumn id="0" isAscending="yes">
						<PSXBackEndColumn id="0">
							<tableAlias>WORKFLOWAPPS</tableAlias>
							<column>WORKFLOWAPPNAME</column>
							<columnAlias/>
						</PSXBackEndColumn>
					</PSXSortedColumn>
				</Sorting>
				<nativeStatement/>
				<Caching enabled="no" type="interval">
					<ageInterval>15</ageInterval>
				</Caching>
			</PSXDataSelector>
			<PSXResourceCacheSettings enabled="no" id="0">
				<Keys/>
				<Dependencies/>
			</PSXResourceCacheSettings>
		</PSXQueryPipe>
		<PSXPageDataTank id="2186">
			<schemaSource>file:communityworkflowlookup.dtd</schemaSource>
			<actionTypeXmlField/>
		</PSXPageDataTank>
		<PSXRequestor directDataStream="no" id="0">
			<requestPage>communityworkflowlookup</requestPage>
			<SelectionParams/>
			<ValidationRules/>
			<characterEncoding>UTF-8</characterEncoding>
			<MimeProperties>
				<html>
					<PSXTextLiteral id="0">
						<text>text/html</text>
					</PSXTextLiteral>
				</html>
				<htm>
					<PSXTextLiteral id="0">
						<text>text/html</text>
					</PSXTextLiteral>
				</htm>
			</MimeProperties>
		</PSXRequestor>
		<PSXResultPageSet id="0">
			<PSXResultPage allowNamespaceCleanup="false" id="2189">
				<extensionsSupported/>
			</PSXResultPage>
		</PSXResultPageSet>
		<PSXResultPager id="51">
			<maxRowsPerPage>-1</maxRowsPerPage>
			<maxPages>-1</maxPages>
			<maxPageLinks>10</maxPageLinks>
		</PSXResultPager>
	</PSXDataSet>
	<PSXDataSet id="2191">
		<name>Dataset277</name>
		<description/>
		<transactionType>none</transactionType>
		<PSXQueryPipe id="1261">
			<name>QueryPipe</name>
			<description/>
			<PSXBackEndDataTank id="1256">
				<PSXBackEndTable id="1255">
					<alias>WORKFLOWAPPS</alias>
					<table>WORKFLOWAPPS</table>
					<datasource/>
				</PSXBackEndTable>
			</PSXBackEndDataTank>
			<PSXDataMapper id="1259" returnEmptyXml="no">
				<PSXDataMapping groupId="1" id="0">
					<PSXXmlField id="0">
						<name>workflowlookup/workflow/id</name>
					</PSXXmlField>
					<PSXBackEndColumn id="0">
						<tableAlias>WORKFLOWAPPS</tableAlias>
						<column>WORKFLOWAPPID</column>
						<columnAlias/>
					</PSXBackEndColumn>
					<Conditionals/>
				</PSXDataMapping>
				<PSXDataMapping groupId="1" id="0">
					<PSXXmlField id="0">
						<name>workflowlookup/workflow/name</name>
					</PSXXmlField>
					<PSXExtensionCall id="0">
						<name>Java/i18n/sys_LocalizedTextLookupUser</name>
						<PSXExtensionParamValue id="0">
							<value>
								<PSXTextLiteral id="0">
									<text>psx.workflow.workflow</text>
								</PSXTextLiteral>
							</value>
						</PSXExtensionParamValue>
						<PSXExtensionParamValue id="0">
							<value>
								<PSXBackEndColumn id="0">
									<tableAlias>WORKFLOWAPPS</tableAlias>
									<column>WORKFLOWAPPID</column>
									<columnAlias/>
								</PSXBackEndColumn>
							</value>
						</PSXExtensionParamValue>
						<PSXExtensionParamValue id="0">
							<value>
								<PSXBackEndColumn id="0">
									<tableAlias>WORKFLOWAPPS</tableAlias>
									<column>WORKFLOWAPPNAME</column>
									<columnAlias/>
								</PSXBackEndColumn>
							</value>
						</PSXExtensionParamValue>
						<PSXExtensionParamValue id="0">
							<value>
								<PSXTextLiteral id="0">
									<text/>
								</PSXTextLiteral>
							</value>
						</PSXExtensionParamValue>
						<PSXExtensionParamValue id="0">
							<value>
								<PSXTextLiteral id="0">
									<text/>
								</PSXTextLiteral>
							</value>
						</PSXExtensionParamValue>
						<PSXExtensionParamValue id="0">
							<value>
								<PSXTextLiteral id="0">
									<text/>
								</PSXTextLiteral>
							</value>
						</PSXExtensionParamValue>
						<PSXExtensionParamValue id="0">
							<value>
								<PSXTextLiteral id="0">
									<text/>
								</PSXTextLiteral>
							</value>
						</PSXExtensionParamValue>
						<PSXExtensionParamValue id="0">
							<value>
								<PSXTextLiteral id="0">
									<text/>
								</PSXTextLiteral>
							</value>
						</PSXExtensionParamValue>
					</PSXExtensionCall>
					<Conditionals/>
				</PSXDataMapping>
			</PSXDataMapper>
			<PSXDataSelector id="1257" method="whereClause" unique="no">
				<WhereClauses/>
				<Sorting>
					<PSXSortedColumn id="0" isAscending="yes">
						<PSXBackEndColumn id="0">
							<tableAlias>WORKFLOWAPPS</tableAlias>
							<column>WORKFLOWAPPNAME</column>
							<columnAlias/>
						</PSXBackEndColumn>
					</PSXSortedColumn>
				</Sorting>
				<nativeStatement/>
				<Caching enabled="no" type="interval">
					<ageInterval>15</ageInterval>
				</Caching>
			</PSXDataSelector>
			<PSXResourceCacheSettings enabled="no" id="0">
				<Keys/>
				<Dependencies/>
			</PSXResourceCacheSettings>
		</PSXQueryPipe>
		<PSXPageDataTank id="2190">
			<schemaSource>file:workflowlookup.dtd</schemaSource>
			<actionTypeXmlField/>
		</PSXPageDataTank>
		<PSXRequestor directDataStream="no" id="0">
			<requestPage>workflowlookup</requestPage>
			<SelectionParams/>
			<ValidationRules/>
			<characterEncoding>UTF-8</characterEncoding>
			<MimeProperties>
				<html>
					<PSXTextLiteral id="0">
						<text>text/html</text>
					</PSXTextLiteral>
				</html>
				<htm>
					<PSXTextLiteral id="0">
						<text>text/html</text>
					</PSXTextLiteral>
				</htm>
			</MimeProperties>
		</PSXRequestor>
		<PSXResultPageSet id="0">
			<PSXResultPage allowNamespaceCleanup="false" id="2189">
				<extensionsSupported/>
			</PSXResultPage>
		</PSXResultPageSet>
		<PSXResultPager id="1258">
			<maxRowsPerPage>-1</maxRowsPerPage>
			<maxPages>-1</maxPages>
			<maxPageLinks>10</maxPageLinks>
		</PSXResultPager>
	</PSXDataSet>
	<PSXDataSet id="2193">
		<name>Dataset55</name>
		<description>Gets the workflow status, the stae name and the             information whether or not this is a public state.</description>
		<transactionType>none</transactionType>
		<PSXQueryPipe id="933">
			<name>QueryPipe</name>
			<description/>
			<PSXBackEndDataTank id="929">
				<PSXBackEndTable id="927">
					<alias>STATES</alias>
					<table>STATES</table>
					<datasource/>
				</PSXBackEndTable>
				<PSXBackEndTable id="928">
					<alias>WORKFLOWAPPS</alias>
					<table>WORKFLOWAPPS</table>
					<datasource/>
				</PSXBackEndTable>
				<PSXBackEndJoin id="0" joinType="inner">
					<leftColumn>
						<PSXBackEndColumn id="0">
							<tableAlias>WORKFLOWAPPS</tableAlias>
							<column>WORKFLOWAPPID</column>
							<columnAlias/>
						</PSXBackEndColumn>
					</leftColumn>
					<rightColumn>
						<PSXBackEndColumn id="0">
							<tableAlias>STATES</tableAlias>
							<column>WORKFLOWAPPID</column>
							<columnAlias/>
						</PSXBackEndColumn>
					</rightColumn>
				</PSXBackEndJoin>
			</PSXBackEndDataTank>
			<PSXDataMapper id="931" returnEmptyXml="yes">
				<PSXDataMapping groupId="1" id="0">
					<PSXXmlField id="0">
						<name>WorkflowStatus/@state</name>
					</PSXXmlField>
					<PSXBackEndColumn id="0">
						<tableAlias>STATES</tableAlias>
						<column>STATENAME</column>
						<columnAlias/>
					</PSXBackEndColumn>
					<Conditionals/>
				</PSXDataMapping>
				<PSXDataMapping groupId="1" id="0">
					<PSXXmlField id="0">
						<name>WorkflowStatus/@isPublic</name>
					</PSXXmlField>
					<PSXBackEndColumn id="0">
						<tableAlias>STATES</tableAlias>
						<column>CONTENTVALID</column>
						<columnAlias/>
					</PSXBackEndColumn>
					<Conditionals/>
				</PSXDataMapping>
			</PSXDataMapper>
			<PSXDataSelector id="930" method="whereClause" unique="no">
				<WhereClauses>
					<PSXWhereClause id="0" omitWhenNull="no">
						<PSXConditional id="0">
							<variable>
								<PSXBackEndColumn id="0">
									<tableAlias>WORKFLOWAPPS</tableAlias>
									<column>WORKFLOWAPPID</column>
									<columnAlias/>
								</PSXBackEndColumn>
							</variable>
							<operator>=</operator>
							<value>
								<PSXSingleHtmlParameter id="0">
									<name>sys_workflowid</name>
								</PSXSingleHtmlParameter>
							</value>
							<boolean>AND</boolean>
						</PSXConditional>
					</PSXWhereClause>
					<PSXWhereClause id="0" omitWhenNull="no">
						<PSXConditional id="0">
							<variable>
								<PSXBackEndColumn id="0">
									<tableAlias>STATES</tableAlias>
									<column>STATEID</column>
									<columnAlias/>
								</PSXBackEndColumn>
							</variable>
							<operator>=</operator>
							<value>
								<PSXSingleHtmlParameter id="0">
									<name>newstateid</name>
								</PSXSingleHtmlParameter>
							</value>
							<boolean>AND</boolean>
						</PSXConditional>
					</PSXWhereClause>
				</WhereClauses>
				<Sorting/>
				<nativeStatement/>
				<Caching enabled="no" type="interval">
					<ageInterval>15</ageInterval>
				</Caching>
			</PSXDataSelector>
			<PSXResourceCacheSettings enabled="no" id="0">
				<Keys/>
				<Dependencies/>
			</PSXResourceCacheSettings>
		</PSXQueryPipe>
		<PSXPageDataTank id="2192">
			<schemaSource>file:WorkflowStatus.dtd</schemaSource>
			<actionTypeXmlField/>
		</PSXPageDataTank>
		<PSXRequestor directDataStream="no" id="0">
			<requestPage>getWorkflowStatus</requestPage>
			<SelectionParams/>
			<ValidationRules/>
			<characterEncoding>UTF-8</characterEncoding>
			<MimeProperties>
				<html>
					<PSXTextLiteral id="0">
						<text>text/html</text>
					</PSXTextLiteral>
				</html>
				<htm>
					<PSXTextLiteral id="0">
						<text>text/html</text>
					</PSXTextLiteral>
				</htm>
			</MimeProperties>
		</PSXRequestor>
		<PSXResultPageSet id="0">
			<PSXResultPage allowNamespaceCleanup="false" id="2194">
				<extensionsSupported/>
			</PSXResultPage>
		</PSXResultPageSet>
	</PSXDataSet>
	<PSXDataSet id="2196">
		<name>Dataset137</name>
		<description>Gets a list of transitions for the supplied             workflow and state id. The list is ordered by transition name.</description>
		<transactionType>none</transactionType>
		<PSXQueryPipe id="408">
			<name>QueryPipe</name>
			<description/>
			<PSXBackEndDataTank id="403">
				<PSXBackEndTable id="400">
					<alias>WORKFLOWAPPS</alias>
					<table>WORKFLOWAPPS</table>
					<datasource/>
				</PSXBackEndTable>
				<PSXBackEndTable id="401">
					<alias>TRANSITIONS</alias>
					<table>TRANSITIONS</table>
					<datasource/>
				</PSXBackEndTable>
				<PSXBackEndTable id="402">
					<alias>STATES</alias>
					<table>STATES</table>
					<datasource/>
				</PSXBackEndTable>
				<PSXBackEndJoin id="0" joinType="inner">
					<leftColumn>
						<PSXBackEndColumn id="0">
							<tableAlias>WORKFLOWAPPS</tableAlias>
							<column>WORKFLOWAPPID</column>
							<columnAlias/>
						</PSXBackEndColumn>
					</leftColumn>
					<rightColumn>
						<PSXBackEndColumn id="0">
							<tableAlias>TRANSITIONS</tableAlias>
							<column>WORKFLOWAPPID</column>
							<columnAlias/>
						</PSXBackEndColumn>
					</rightColumn>
				</PSXBackEndJoin>
				<PSXBackEndJoin id="0" joinType="inner">
					<leftColumn>
						<PSXBackEndColumn id="0">
							<tableAlias>WORKFLOWAPPS</tableAlias>
							<column>WORKFLOWAPPID</column>
							<columnAlias/>
						</PSXBackEndColumn>
					</leftColumn>
					<rightColumn>
						<PSXBackEndColumn id="0">
							<tableAlias>STATES</tableAlias>
							<column>WORKFLOWAPPID</column>
							<columnAlias/>
						</PSXBackEndColumn>
					</rightColumn>
				</PSXBackEndJoin>
				<PSXBackEndJoin id="0" joinType="inner">
					<leftColumn>
						<PSXBackEndColumn id="0">
							<tableAlias>STATES</tableAlias>
							<column>STATEID</column>
							<columnAlias/>
						</PSXBackEndColumn>
					</leftColumn>
					<rightColumn>
						<PSXBackEndColumn id="0">
							<tableAlias>TRANSITIONS</tableAlias>
							<column>TRANSITIONFROMSTATEID</column>
							<columnAlias/>
						</PSXBackEndColumn>
					</rightColumn>
				</PSXBackEndJoin>
			</PSXBackEndDataTank>
			<PSXDataMapper id="406" returnEmptyXml="yes">
				<PSXDataMapping groupId="1" id="0">
					<PSXXmlField id="0">
						<name>Transitions/Transition/@name</name>
					</PSXXmlField>
					<PSXBackEndColumn id="0">
						<tableAlias>TRANSITIONS</tableAlias>
						<column>TRANSITIONACTIONTRIGGER</column>
						<columnAlias/>
					</PSXBackEndColumn>
					<Conditionals/>
				</PSXDataMapping>
				<PSXDataMapping groupId="1" id="0">
					<PSXXmlField id="0">
						<name>Transitions/Transition/@isDefault</name>
					</PSXXmlField>
					<PSXBackEndColumn id="0">
						<tableAlias>TRANSITIONS</tableAlias>
						<column>DEFAULTTRANSITION</column>
						<columnAlias/>
					</PSXBackEndColumn>
					<Conditionals/>
				</PSXDataMapping>
			</PSXDataMapper>
			<PSXDataSelector id="404" method="whereClause" unique="no">
				<WhereClauses>
					<PSXWhereClause id="0" omitWhenNull="no">
						<PSXConditional id="0">
							<variable>
								<PSXBackEndColumn id="0">
									<tableAlias>WORKFLOWAPPS</tableAlias>
									<column>WORKFLOWAPPID</column>
									<columnAlias/>
								</PSXBackEndColumn>
							</variable>
							<operator>=</operator>
							<value>
								<PSXSingleHtmlParameter id="0">
									<name>sys_workflowid</name>
								</PSXSingleHtmlParameter>
							</value>
							<boolean>AND</boolean>
						</PSXConditional>
					</PSXWhereClause>
					<PSXWhereClause id="0" omitWhenNull="no">
						<PSXConditional id="0">
							<variable>
								<PSXBackEndColumn id="0">
									<tableAlias>STATES</tableAlias>
									<column>STATEID</column>
									<columnAlias/>
								</PSXBackEndColumn>
							</variable>
							<operator>=</operator>
							<value>
								<PSXSingleHtmlParameter id="0">
									<name>newstateid</name>
								</PSXSingleHtmlParameter>
							</value>
							<boolean>AND</boolean>
						</PSXConditional>
					</PSXWhereClause>
				</WhereClauses>
				<Sorting>
					<PSXSortedColumn id="0" isAscending="yes">
						<PSXBackEndColumn id="0">
							<tableAlias>TRANSITIONS</tableAlias>
							<column>TRANSITIONLABEL</column>
							<columnAlias/>
						</PSXBackEndColumn>
					</PSXSortedColumn>
				</Sorting>
				<nativeStatement/>
				<Caching enabled="no" type="interval">
					<ageInterval>15</ageInterval>
				</Caching>
			</PSXDataSelector>
			<PSXResourceCacheSettings enabled="no" id="0">
				<Keys/>
				<Dependencies/>
			</PSXResourceCacheSettings>
		</PSXQueryPipe>
		<PSXPageDataTank id="2195">
			<schemaSource>file:Transitions.dtd</schemaSource>
			<actionTypeXmlField/>
		</PSXPageDataTank>
		<PSXRequestor directDataStream="no" id="0">
			<requestPage>getTransitions</requestPage>
			<SelectionParams/>
			<ValidationRules/>
			<characterEncoding>UTF-8</characterEncoding>
			<MimeProperties>
				<html>
					<PSXTextLiteral id="0">
						<text>text/html</text>
					</PSXTextLiteral>
				</html>
				<htm>
					<PSXTextLiteral id="0">
						<text>text/html</text>
					</PSXTextLiteral>
				</htm>
			</MimeProperties>
		</PSXRequestor>
		<PSXResultPageSet id="0">
			<PSXResultPage allowNamespaceCleanup="false" id="2197">
				<extensionsSupported/>
			</PSXResultPage>
		</PSXResultPageSet>
		<PSXResultPager id="405">
			<maxRowsPerPage>-1</maxRowsPerPage>
			<maxPages>-1</maxPages>
			<maxPageLinks>10</maxPageLinks>
		</PSXResultPager>
	</PSXDataSet>
	<PSXDataSet id="2199">
		<name>Dataset497</name>
		<description>Get the transition information for the supplied content id, workflow id and workflow action trigger.</description>
		<transactionType>none</transactionType>
		<PSXQueryPipe id="994">
			<name>QueryPipe</name>
			<description/>
			<PSXBackEndDataTank id="990">
				<PSXBackEndTable id="988">
					<alias>TRANSITIONS</alias>
					<table>TRANSITIONS</table>
					<datasource/>
				</PSXBackEndTable>
				<PSXBackEndTable id="989">
					<alias>CONTENTSTATUS</alias>
					<table>CONTENTSTATUS</table>
					<datasource/>
				</PSXBackEndTable>
				<PSXBackEndJoin id="0" joinType="inner">
					<leftColumn>
						<PSXBackEndColumn id="0">
							<tableAlias>CONTENTSTATUS</tableAlias>
							<column>CONTENTSTATEID</column>
							<columnAlias/>
						</PSXBackEndColumn>
					</leftColumn>
					<rightColumn>
						<PSXBackEndColumn id="0">
							<tableAlias>TRANSITIONS</tableAlias>
							<column>TRANSITIONFROMSTATEID</column>
							<columnAlias/>
						</PSXBackEndColumn>
					</rightColumn>
				</PSXBackEndJoin>
				<PSXBackEndJoin id="0" joinType="inner">
					<leftColumn>
						<PSXBackEndColumn id="0">
							<tableAlias>CONTENTSTATUS</tableAlias>
							<column>WORKFLOWAPPID</column>
							<columnAlias/>
						</PSXBackEndColumn>
					</leftColumn>
					<rightColumn>
						<PSXBackEndColumn id="0">
							<tableAlias>TRANSITIONS</tableAlias>
							<column>WORKFLOWAPPID</column>
							<columnAlias/>
						</PSXBackEndColumn>
					</rightColumn>
				</PSXBackEndJoin>
			</PSXBackEndDataTank>
			<PSXDataMapper id="992" returnEmptyXml="yes">
				<PSXDataMapping groupId="1" id="0">
					<PSXXmlField id="0">
						<name>RequestedTransition/@transition</name>
					</PSXXmlField>
					<PSXBackEndColumn id="0">
						<tableAlias>TRANSITIONS</tableAlias>
						<column>TRANSITIONACTIONTRIGGER</column>
						<columnAlias/>
					</PSXBackEndColumn>
					<Conditionals/>
				</PSXDataMapping>
				<PSXDataMapping groupId="1" id="0">
					<PSXXmlField id="0">
						<name>RequestedTransition/@fromStateId</name>
					</PSXXmlField>
					<PSXBackEndColumn id="0">
						<tableAlias>TRANSITIONS</tableAlias>
						<column>TRANSITIONFROMSTATEID</column>
						<columnAlias/>
					</PSXBackEndColumn>
					<Conditionals/>
				</PSXDataMapping>
				<PSXDataMapping groupId="1" id="0">
					<PSXXmlField id="0">
						<name>RequestedTransition/@toStateId</name>
					</PSXXmlField>
					<PSXBackEndColumn id="0">
						<tableAlias>TRANSITIONS</tableAlias>
						<column>TRANSITIONTOSTATEID</column>
						<columnAlias/>
					</PSXBackEndColumn>
					<Conditionals/>
				</PSXDataMapping>
				<PSXDataMapping groupId="1" id="0">
					<PSXXmlField id="0">
						<name>RequestedTransition/@wfId</name>
					</PSXXmlField>
					<PSXBackEndColumn id="0">
						<tableAlias>TRANSITIONS</tableAlias>
						<column>WORKFLOWAPPID</column>
						<columnAlias/>
					</PSXBackEndColumn>
					<Conditionals/>
				</PSXDataMapping>
			</PSXDataMapper>
			<PSXDataSelector id="991" method="whereClause" unique="no">
				<WhereClauses>
					<PSXWhereClause id="0" omitWhenNull="no">
						<PSXConditional id="0">
							<variable>
								<PSXBackEndColumn id="0">
									<tableAlias>CONTENTSTATUS</tableAlias>
									<column>CONTENTID</column>
									<columnAlias/>
								</PSXBackEndColumn>
							</variable>
							<operator>=</operator>
							<value>
								<PSXSingleHtmlParameter id="0">
									<name>sys_contentid</name>
								</PSXSingleHtmlParameter>
							</value>
							<boolean>AND</boolean>
						</PSXConditional>
					</PSXWhereClause>
					<PSXWhereClause id="0" omitWhenNull="no">
						<PSXConditional id="0">
							<variable>
								<PSXBackEndColumn id="0">
									<tableAlias>TRANSITIONS</tableAlias>
									<column>TRANSITIONACTIONTRIGGER</column>
									<columnAlias/>
								</PSXBackEndColumn>
							</variable>
							<operator>=</operator>
							<value>
								<PSXSingleHtmlParameter id="0">
									<name>WFAction</name>
								</PSXSingleHtmlParameter>
							</value>
							<boolean>AND</boolean>
						</PSXConditional>
					</PSXWhereClause>
				</WhereClauses>
				<Sorting/>
				<nativeStatement/>
				<Caching enabled="no" type="interval">
					<ageInterval>15</ageInterval>
				</Caching>
			</PSXDataSelector>
			<PSXResourceCacheSettings enabled="no" id="0">
				<Keys/>
				<Dependencies/>
			</PSXResourceCacheSettings>
		</PSXQueryPipe>
		<PSXPageDataTank id="2198">
			<schemaSource>file:RequestedTransition.dtd</schemaSource>
			<actionTypeXmlField/>
		</PSXPageDataTank>
		<PSXRequestor directDataStream="no" id="0">
			<requestPage>getRequestedTransition</requestPage>
			<SelectionParams/>
			<ValidationRules/>
			<characterEncoding>UTF-8</characterEncoding>
			<MimeProperties>
				<html>
					<PSXTextLiteral id="0">
						<text>text/html</text>
					</PSXTextLiteral>
				</html>
				<htm>
					<PSXTextLiteral id="0">
						<text>text/html</text>
					</PSXTextLiteral>
				</htm>
			</MimeProperties>
		</PSXRequestor>
		<PSXResultPageSet id="0">
			<PSXResultPage allowNamespaceCleanup="false" id="2200">
				<extensionsSupported/>
			</PSXResultPage>
		</PSXResultPageSet>
	</PSXDataSet>
	<PSXDataSet id="2202">
		<name>Dataset934</name>
		<description>Gets the current workflow status information for             the supplied content id.</description>
		<transactionType>none</transactionType>
		<PSXQueryPipe id="2163">
			<name>QueryPipe</name>
			<description/>
			<PSXBackEndDataTank id="2159">
				<PSXBackEndTable id="2157">
					<alias>STATES</alias>
					<table>STATES</table>
					<datasource/>
				</PSXBackEndTable>
				<PSXBackEndTable id="2158">
					<alias>CONTENTSTATUS</alias>
					<table>CONTENTSTATUS</table>
					<datasource/>
				</PSXBackEndTable>
				<PSXBackEndJoin id="0" joinType="inner">
					<leftColumn>
						<PSXBackEndColumn id="0">
							<tableAlias>CONTENTSTATUS</tableAlias>
							<column>CONTENTSTATEID</column>
							<columnAlias/>
						</PSXBackEndColumn>
					</leftColumn>
					<rightColumn>
						<PSXBackEndColumn id="0">
							<tableAlias>STATES</tableAlias>
							<column>STATEID</column>
							<columnAlias/>
						</PSXBackEndColumn>
					</rightColumn>
				</PSXBackEndJoin>
				<PSXBackEndJoin id="0" joinType="inner">
					<leftColumn>
						<PSXBackEndColumn id="0">
							<tableAlias>CONTENTSTATUS</tableAlias>
							<column>WORKFLOWAPPID</column>
							<columnAlias/>
						</PSXBackEndColumn>
					</leftColumn>
					<rightColumn>
						<PSXBackEndColumn id="0">
							<tableAlias>STATES</tableAlias>
							<column>WORKFLOWAPPID</column>
							<columnAlias/>
						</PSXBackEndColumn>
					</rightColumn>
				</PSXBackEndJoin>
			</PSXBackEndDataTank>
			<PSXDataMapper id="2161" returnEmptyXml="yes">
				<PSXDataMapping groupId="1" id="0">
					<PSXXmlField id="0">
						<name>CurrentState/@workflowId</name>
					</PSXXmlField>
					<PSXBackEndColumn id="0">
						<tableAlias>STATES</tableAlias>
						<column>WORKFLOWAPPID</column>
						<columnAlias/>
					</PSXBackEndColumn>
					<Conditionals/>
				</PSXDataMapping>
				<PSXDataMapping groupId="1" id="0">
					<PSXXmlField id="0">
						<name>CurrentState/@stateId</name>
					</PSXXmlField>
					<PSXBackEndColumn id="0">
						<tableAlias>STATES</tableAlias>
						<column>STATEID</column>
						<columnAlias/>
					</PSXBackEndColumn>
					<Conditionals/>
				</PSXDataMapping>
				<PSXDataMapping groupId="1" id="0">
					<PSXXmlField id="0">
						<name>CurrentState/@stateName</name>
					</PSXXmlField>
					<PSXBackEndColumn id="0">
						<tableAlias>STATES</tableAlias>
						<column>STATENAME</column>
						<columnAlias/>
					</PSXBackEndColumn>
					<Conditionals/>
				</PSXDataMapping>
				<PSXDataMapping groupId="1" id="0">
					<PSXXmlField id="0">
						<name>CurrentState/@isPublic</name>
					</PSXXmlField>
					<PSXBackEndColumn id="0">
						<tableAlias>STATES</tableAlias>
						<column>CONTENTVALID</column>
						<columnAlias/>
					</PSXBackEndColumn>
					<Conditionals/>
				</PSXDataMapping>
			</PSXDataMapper>
			<PSXDataSelector id="2160" method="whereClause" unique="no">
				<WhereClauses>
					<PSXWhereClause id="0" omitWhenNull="no">
						<PSXConditional id="0">
							<variable>
								<PSXBackEndColumn id="0">
									<tableAlias>CONTENTSTATUS</tableAlias>
									<column>CONTENTID</column>
									<columnAlias/>
								</PSXBackEndColumn>
							</variable>
							<operator>=</operator>
							<value>
								<PSXSingleHtmlParameter id="0">
									<name>sys_contentid</name>
								</PSXSingleHtmlParameter>
							</value>
							<boolean>AND</boolean>
						</PSXConditional>
					</PSXWhereClause>
				</WhereClauses>
				<Sorting/>
				<nativeStatement/>
				<Caching enabled="no" type="interval">
					<ageInterval>15</ageInterval>
				</Caching>
			</PSXDataSelector>
			<PSXResourceCacheSettings enabled="no" id="0">
				<Keys/>
				<Dependencies/>
			</PSXResourceCacheSettings>
		</PSXQueryPipe>
		<PSXPageDataTank id="2201">
			<schemaSource>file:CurrentState.dtd</schemaSource>
			<actionTypeXmlField/>
		</PSXPageDataTank>
		<PSXRequestor directDataStream="no" id="0">
			<requestPage>getCurrentState</requestPage>
			<SelectionParams>
				<PSXConditional id="0">
					<variable>
						<PSXHtmlParameter id="0">
							<name>sys_contentids</name>
						</PSXHtmlParameter>
					</variable>
					<operator>IS NULL</operator>
					<boolean>AND</boolean>
				</PSXConditional>
			</SelectionParams>
			<ValidationRules/>
			<characterEncoding>UTF-8</characterEncoding>
			<MimeProperties>
				<html>
					<PSXTextLiteral id="0">
						<text>text/html</text>
					</PSXTextLiteral>
				</html>
				<htm>
					<PSXTextLiteral id="0">
						<text>text/html</text>
					</PSXTextLiteral>
				</htm>
			</MimeProperties>
		</PSXRequestor>
		<PSXResultPageSet id="0">
			<PSXResultPage allowNamespaceCleanup="false" id="2203">
				<extensionsSupported/>
			</PSXResultPage>
		</PSXResultPageSet>
	</PSXDataSet>
	<PSXDataSet id="2205">
		<name>Dataset547</name>
		<description/>
		<transactionType>none</transactionType>
		<PSXQueryPipe id="662">
			<name>QueryPipe</name>
			<description/>
			<PSXBackEndDataTank id="658">
				<PSXBackEndTable id="657">
					<alias>RXSLOTTYPE</alias>
					<table>RXSLOTTYPE</table>
					<datasource/>
				</PSXBackEndTable>
			</PSXBackEndDataTank>
			<PSXDataMapper id="660" returnEmptyXml="no">
				<PSXDataMapping groupId="1" id="0">
					<PSXXmlField id="0">
						<name>Slots/Slot/@slotid</name>
					</PSXXmlField>
					<PSXBackEndColumn id="0">
						<tableAlias>RXSLOTTYPE</tableAlias>
						<column>SLOTID</column>
						<columnAlias/>
					</PSXBackEndColumn>
					<Conditionals/>
				</PSXDataMapping>
				<PSXDataMapping groupId="1" id="0">
					<PSXXmlField id="0">
						<name>Slots/Slot/@aaRelType</name>
					</PSXXmlField>
					<PSXBackEndColumn id="0">
						<tableAlias>RXSLOTTYPE</tableAlias>
						<column>RELATIONSHIPNAME</column>
						<columnAlias/>
					</PSXBackEndColumn>
					<Conditionals/>
				</PSXDataMapping>
			</PSXDataMapper>
			<PSXDataSelector id="659" method="whereClause" unique="no">
				<WhereClauses>
					<PSXWhereClause id="0" omitWhenNull="no">
						<PSXConditional id="0">
							<variable>
								<PSXBackEndColumn id="0">
									<tableAlias>RXSLOTTYPE</tableAlias>
									<column>SLOTID</column>
									<columnAlias/>
								</PSXBackEndColumn>
							</variable>
							<operator>=</operator>
							<value>
								<PSXSingleHtmlParameter id="0">
									<name>sys_slotid</name>
								</PSXSingleHtmlParameter>
							</value>
							<boolean>AND</boolean>
						</PSXConditional>
					</PSXWhereClause>
				</WhereClauses>
				<Sorting/>
				<nativeStatement/>
				<Caching enabled="no" type="interval">
					<ageInterval>15</ageInterval>
				</Caching>
			</PSXDataSelector>
			<PSXResourceCacheSettings enabled="no" id="0">
				<Keys/>
				<Dependencies/>
			</PSXResourceCacheSettings>
		</PSXQueryPipe>
		<PSXPageDataTank id="2204">
			<schemaSource>file:Slots.dtd</schemaSource>
			<actionTypeXmlField/>
		</PSXPageDataTank>
		<PSXRequestor directDataStream="no" id="0">
			<requestPage>slotrelation</requestPage>
			<SelectionParams/>
			<ValidationRules/>
			<characterEncoding>UTF-8</characterEncoding>
			<MimeProperties>
				<html>
					<PSXTextLiteral id="0">
						<text>text/html</text>
					</PSXTextLiteral>
				</html>
				<htm>
					<PSXTextLiteral id="0">
						<text>text/html</text>
					</PSXTextLiteral>
				</htm>
			</MimeProperties>
		</PSXRequestor>
		<PSXResultPageSet id="0">
			<PSXResultPage allowNamespaceCleanup="false" id="2206">
				<extensionsSupported/>
			</PSXResultPage>
		</PSXResultPageSet>
	</PSXDataSet>
	<PSXLogger id="0" logAppStartStop="yes" logAppStatistics="no" logBasicUserActivity="no" logDetailedUserActivity="no" logErrors="no" logExecutionPlan="no" logFullUserActivity="no" logMultipleHandlers="no" logServerStartStop="no"/>
	<PSXTraceInfo id="0" traceAppHandlerProc="no" traceAppSecurity="no" traceBasicRequestInfo="no" traceConditionalEval="no" traceDbPool="no" traceEnabled="no" traceExitExec="no" traceExitProc="no" traceFileInfo="no" traceInitHttpVar="no" traceMapper="no" traceOutputColumnWidth="80" traceOutputConv="no" tracePostExitCgi="no" tracePostExitXml="no" tracePostPreProcHttpVar="no" traceResourceHandler="no" traceResultSet="no" traceSessionInfo="no" traceTimestampOnlyEnabled="no"/>
	<PSXErrorWebPages id="2164" returnHtml="yes"/>
	<backEndLoginPassthru>no</backEndLoginPassthru>
	<PSXNotifier id="2165">
		<providerType>SMTP</providerType>
		<server>//Ben</server>
		<from/>
	</PSXNotifier>
	<userProperty name="schemaSourceReadOnly2176">true</userProperty>
	<userProperty name="schemaSourceReadOnly2172">false</userProperty>
	<userProperty name="locationY2178">238</userProperty>
	<userProperty name="locationY2177">239</userProperty>
	<userProperty name="pageDatatankFilePath2179">C:\data\specs\i18n\PSXRelationshipSet.dtd</userProperty>
	<userProperty name="locationY2175">22</userProperty>
	<userProperty name="locationY2174">122</userProperty>
	<userProperty name="locationX2189">170</userProperty>
	<userProperty name="locationY2173">116</userProperty>
	<userProperty name="locationX2188">170</userProperty>
	<userProperty name="locationX2187">8</userProperty>
	<userProperty name="locationY2171">131</userProperty>
	<userProperty name="locationY2170">115</userProperty>
	<userProperty name="locationX2185">377</userProperty>
	<userProperty name="locationX2184">241</userProperty>
	<userProperty name="locationX2182">62</userProperty>
	<userProperty name="locationX2181">380</userProperty>
	<userProperty name="schemaSourceReadOnly2204">false</userProperty>
	<userProperty name="locationX2180">258</userProperty>
	<userProperty name="schemaSourceReadOnly2201">true</userProperty>
	<userProperty name="schemaSourceReadOnly2169">true</userProperty>
	<userProperty name="schemaSourceReadOnly2166">false</userProperty>
	<userProperty name="locationY2206">488</userProperty>
	<userProperty name="locationY2205">475</userProperty>
	<userProperty name="locationY2203">362</userProperty>
	<userProperty name="locationY2202">350</userProperty>
	<userProperty name="locationY2201">0</userProperty>
	<userProperty name="locationY2200">242</userProperty>
	<userProperty name="pageDatatankFilePath2201">C:\data\cx\codereview\CurrentState.dtd</userProperty>
	<userProperty name="locationY2168">18</userProperty>
	<userProperty name="locationY2167">10</userProperty>
	<userProperty name="pageDatatankFilePath2169">D:\rx\installs\rx56rsTest\sys_psxRelationshipSupport\getContentTypes.dtd</userProperty>
	<userProperty name="locationY2165">55</userProperty>
	<userProperty name="locationY2164">10</userProperty>
	<userProperty name="locationX2178">371</userProperty>
	<userProperty name="locationX2177">254</userProperty>
	<userProperty name="locationX2175">59</userProperty>
	<userProperty name="locationX2174">371</userProperty>
	<userProperty name="locationX2173">252</userProperty>
	<userProperty name="locationX2171">160</userProperty>
	<userProperty name="locationX2170">22</userProperty>
	<userProperty name="pageDatatankSrcType2198">2</userProperty>
	<userProperty name="pageDatatankSrcType2195">2</userProperty>
	<userProperty name="pageDatatankSrcType2192">2</userProperty>
	<userProperty name="pageDatatankSrcType2190">2</userProperty>
	<userProperty name="locationX2206">134</userProperty>
	<userProperty name="locationX2205">28</userProperty>
	<userProperty name="resultPageFilePath2197">C:\data\cx\codereview\Transitions.dtd</userProperty>
	<userProperty name="locationX2203">616</userProperty>
	<userProperty name="locationX2202">496</userProperty>
	<userProperty name="resultPageFilePath2194">C:\data\cx\codereview\WorkflowStatus.dtd</userProperty>
	<userProperty name="locationX2201">341</userProperty>
	<userProperty name="locationX2200">616</userProperty>
	<userProperty name="locationX2168">153</userProperty>
	<userProperty name="locationX2167">21</userProperty>
	<userProperty name="locationX2165">16</userProperty>
	<userProperty name="locationX2164">16</userProperty>
	<userProperty name="savedFromWorkbench">Yes</userProperty>
	<userProperty name="pageDatatankSrcType2186">2</userProperty>
	<userProperty name="pageDatatankSrcType2183">3</userProperty>
	<userProperty name="resultPageFilePath2181">C:\data\specs\i18n\PSXRelationshipSet.dtd</userProperty>
	<userProperty name="pageDatatankSrcType2179">2</userProperty>
	<userProperty name="pageDatatankSrcType2176">3</userProperty>
	<userProperty name="pageDatatankSrcType2172">3</userProperty>
	<userProperty name="schemaSourceReadOnly2198">true</userProperty>
	<userProperty name="schemaSourceReadOnly2195">true</userProperty>
	<userProperty name="schemaSourceReadOnly2192">true</userProperty>
	<userProperty name="schemaSourceReadOnly2190">true</userProperty>
	<userProperty name="locationY2199">229</userProperty>
	<userProperty name="locationY2197">121</userProperty>
	<userProperty name="pageDatatankSrcType2204">3</userProperty>
	<userProperty name="locationY2196">115</userProperty>
	<userProperty name="pageDatatankFilePath2198">C:\data\cx\codereview\RequestedTransition.dtd</userProperty>
	<userProperty name="locationY2194">17</userProperty>
	<userProperty name="pageDatatankSrcType2201">2</userProperty>
	<userProperty name="locationY2193">9</userProperty>
	<userProperty name="pageDatatankFilePath2195">C:\data\cx\codereview\Transitions.dtd</userProperty>
	<userProperty name="pageDatatankSrcType2169">2</userProperty>
	<userProperty name="locationY2191">344</userProperty>
	<userProperty name="pageDatatankFilePath2192">C:\data\cx\codereview\WorkflowStatus.dtd</userProperty>
	<userProperty name="pageDatatankSrcType2166">3</userProperty>
	<userProperty name="pageDatatankFilePath2190">C:\\workflowlookup.dtd</userProperty>
	<userProperty name="resultPageFilePath2203">C:\data\cx\codereview\CurrentState.dtd</userProperty>
	<userProperty name="resultPageFilePath2200">C:\data\cx\codereview\RequestedTransition.dtd</userProperty>
	<userProperty name="schemaSourceReadOnly2186">true</userProperty>
	<userProperty name="schemaSourceReadOnly2183">false</userProperty>
	<userProperty name="locationY2189">282</userProperty>
	<userProperty name="locationY2188">282</userProperty>
	<userProperty name="locationY2187">224</userProperty>
	<userProperty name="locationY2185">23</userProperty>
	<userProperty name="locationY2184">13</userProperty>
	<userProperty name="locationX2199">479</userProperty>
	<userProperty name="pageDatatankFilePath2186">C:\rx4510925b\sys_uiSupport\communityworkflowlookup.dtd</userProperty>
	<userProperty name="locationY2182">22</userProperty>
	<userProperty name="locationX2197">604</userProperty>
	<userProperty name="locationY2181">352</userProperty>
	<userProperty name="locationX2196">493</userProperty>
	<userProperty name="locationY2180">355</userProperty>
	<userProperty name="locationX2194">602</userProperty>
	<userProperty name="locationX2193">478</userProperty>
	<userProperty name="locationX2191">29</userProperty>
	<userProperty name="schemaSourceReadOnly2179">true</userProperty>
</PSXApplication>
